gitbinding/Git.py
gitbinding/__init__.py
gitbinding/py.typed
gitbinding-1.0.6.dist-info/LICENSE
gitbinding-1.0.6.dist-info/METADATA
gitbinding-1.0.6.dist-info/WHEEL
gitbinding-1.0.6.dist-info/top_level.txt
gitbinding-1.0.6.dist-info/RECORD
