Metadata-Version: 2.1
Name: gitbinding
Version: 1.0.6
Summary: python binding git command.
Home-page: https://github.com/guangrei/Gitpybinding
Author: guangrei
Author-email: myawn@pm.me
License: MIT
Keywords: git
License-File: LICENSE
Requires-Dist: anybinding
